positif/__init__.py
positif/main.py
positif/parameters.py
positif/parser.py
positif-0.0.3.dist-info/LICENSE
positif-0.0.3.dist-info/METADATA
positif-0.0.3.dist-info/WHEEL
positif-0.0.3.dist-info/entry_points.txt
positif-0.0.3.dist-info/top_level.txt
positif-0.0.3.dist-info/RECORD
