Metadata-Version: 2.1
Name: positif
Version: 0.0.3
Summary: Convert colour film negatives digitised by a digital camera to positive images
Author-email: Roman <roman@vintage-camera.pictures>
Project-URL: Homepage, https://github.com/vintage-camera-pictures/positif
Project-URL: Bug Tracker, https://github.com/vintage-camera-pictures/positif/issues
Keywords: convert negatives film photography colour digital camera digitise
Classifier: Programming Language :: Python :: 3
Classifier: License :: OSI Approved :: GNU General Public License v3 (GPLv3)
Classifier: Operating System :: OS Independent
Requires-Python: >=3.11
License-File: LICENSE
Requires-Dist: imageio (>=2.22.4)
Requires-Dist: numpy (>=1.23.4)
Requires-Dist: rawpy (>=0.17.2)
Requires-Dist: scipy (>=1.9.1)
